service_oriented/__init__.py
service_oriented/__version__.py
service_oriented/deployment_environment.py
service_oriented/py.typed
service_oriented/application/__init__.py
service_oriented/application/abstract_composition_root.py
service_oriented/application/base_application.py
service_oriented/application/entry_point_spec.py
service_oriented/application/generic_main.py
service_oriented/application/config/__init__.py
service_oriented/application/config/base_config.py
service_oriented/application/config/yaml_config_settings_source.py
service_oriented/logging/__init__.py
service_oriented/logging/normalized_json_formatter.py
service_oriented/services/__init__.py
service_oriented/services/logger_service/__init__.py
service_oriented/services/logger_service/logger_service.py
service_oriented/services/logger_service/logger_service_with_yaml_logging_config.py
service_oriented-0.0.4.dist-info/LICENSE
service_oriented-0.0.4.dist-info/METADATA
service_oriented-0.0.4.dist-info/WHEEL
service_oriented-0.0.4.dist-info/top_level.txt
service_oriented-0.0.4.dist-info/RECORD
